dymoval-0.9.0.dist-info/METADATA
dymoval-0.9.0.dist-info/WHEEL
dymoval-0.9.0.dist-info/entry_points.txt
dymoval-0.9.0.dist-info/licenses/LICENSE
dymoval/__init__.py
dymoval/config.py
dymoval/dataset.py
dymoval/utils.py
dymoval/validation.py
dymoval_tutorial/.ipynb_checkpoints/dymoval_tutorial-checkpoint.ipynb
dymoval_tutorial/DCMotor.fmu
dymoval_tutorial/DCMotor.svg
dymoval_tutorial/DCMotorModel.py
dymoval_tutorial/DCMotor_measurements.h5
dymoval_tutorial/__init__.py
dymoval_tutorial/dymoval_tutorial.ipynb
dymoval_tutorial/tutorial_debug.py
dymoval_tutorial/virtual_lab.py
dymoval-0.9.0.dist-info/RECORD
