Metadata-Version: 2.1
Name: dymoval
Version: 0.9.0
Summary: Dymoval is a Python package for analyzing measurements data and validate models.
Keywords: data-analysis,modeling,model validation,dataset,data
Author-Email: Ubaldo Tiberi <ubaldo.tiberi@gmail.com>, Ubaldo Tiberi <ubaldo.tiberi@volvo.com>
License: BSD 3-Clause License
Classifier: Programming Language :: Python :: 3
Classifier: License :: OSI Approved :: BSD License
Classifier: Operating System :: OS Independent
Project-URL: Homepage, https://github.com/ubaldot/dymoval
Project-URL: Documentation, https://ubaldot.github.io/dymoval/
Project-URL: Bug Tracker, https://github.com/ubaldot/dymoval/issues
Requires-Python: >=3.10
Requires-Dist: pandas
Requires-Dist: matplotlib
Requires-Dist: scipy
Requires-Dist: control
Requires-Dist: numpy
Requires-Dist: tomli
Requires-Dist: h5py
Requires-Dist: typing_extensions
Provides-Extra: build
Requires-Dist: pdm; extra == "build"
Provides-Extra: dev
Requires-Dist: sphinx; extra == "dev"
Requires-Dist: furo; extra == "dev"
Requires-Dist: sphinx-toolbox; extra == "dev"
Requires-Dist: sphinx-autodoc-typehints; extra == "dev"
Requires-Dist: pytest; extra == "dev"
Requires-Dist: mypy; extra == "dev"
Requires-Dist: ruff; extra == "dev"
Requires-Dist: coverage; extra == "dev"
Requires-Dist: grayskull; extra == "dev"
